Metadata-Version: 2.1
Name: test-ryabov-kaka
Version: 0.9.9
Summary: dangerous
Home-page: UNKNOWN
Author: NuatStanskiy
Author-email: smiril13@mail.ru
License: Apache License, Version 2.0, see LICENSE file
Platform: UNKNOWN
